MANIFEST.in
README.txt
plonetheme.stylized-configure.zcml
pypi_upload.sh
setup.cfg
setup.py
docs/HISTORY.txt
docs/INSTALL.txt
docs/LICENSE.GPL
docs/LICENSE.txt
plonetheme/__init__.py
plonetheme.stylized.egg-info/PKG-INFO
plonetheme.stylized.egg-info/SOURCES.txt
plonetheme.stylized.egg-info/dependency_links.txt
plonetheme.stylized.egg-info/entry_points.txt
plonetheme.stylized.egg-info/namespace_packages.txt
plonetheme.stylized.egg-info/not-zip-safe
plonetheme.stylized.egg-info/paster_plugins.txt
plonetheme.stylized.egg-info/requires.txt
plonetheme.stylized.egg-info/top_level.txt
plonetheme/stylized/__init__.py
plonetheme/stylized/configure.zcml
plonetheme/stylized/profiles.zcml
plonetheme/stylized/setuphandlers.py
plonetheme/stylized/skins.zcml
plonetheme/stylized/tests.py
plonetheme/stylized/version.txt
plonetheme/stylized/browser/__init__.py
plonetheme/stylized/browser/configure.zcml
plonetheme/stylized/browser/interfaces.py
plonetheme/stylized/browser/viewlet.pt
plonetheme/stylized/browser/viewlets.py
plonetheme/stylized/browser/images/README.txt
plonetheme/stylized/browser/images/TN.gif
plonetheme/stylized/browser/images/img01.gif
plonetheme/stylized/browser/images/img02.gif
plonetheme/stylized/browser/images/img03.gif
plonetheme/stylized/browser/images/img04.gif
plonetheme/stylized/browser/images/img05.gif
plonetheme/stylized/browser/images/img06.gif
plonetheme/stylized/browser/images/img07.gif
plonetheme/stylized/browser/images/img08.gif
plonetheme/stylized/browser/stylesheets/README.txt
plonetheme/stylized/browser/stylesheets/main.css
plonetheme/stylized/browser/stylesheets/stylized.css
plonetheme/stylized/profiles/default/cssregistry.xml
plonetheme/stylized/profiles/default/import_steps.xml
plonetheme/stylized/profiles/default/jsregistry.xml
plonetheme/stylized/profiles/default/metadata.xml
plonetheme/stylized/profiles/default/plonetheme.stylized_various.txt
plonetheme/stylized/profiles/default/skins.xml
plonetheme/stylized/profiles/default/viewlets.xml
plonetheme/stylized/skins/plonetheme_stylized_custom_images/CONTENT.txt
plonetheme/stylized/skins/plonetheme_stylized_custom_templates/CONTENT.txt
plonetheme/stylized/skins/plonetheme_stylized_custom_templates/main_template.pt
plonetheme/stylized/skins/plonetheme_stylized_styles/CONTENT.txt
plonetheme/stylized/skins/plonetheme_stylized_styles/base.css.dtml
