Metadata-Version: 1.0
Name: plonetheme.stylized
Version: 0.2
Summary: An installable theme for Plone 3.0 based on the stylized theme by NodeThirtyThree.
Home-page: http://svn.plone.org/svn/collective/
Author: Timo Stollenwerk
Author-email: timo@zmag.de
License: GPL
Keywords: web zope plone theme
Platform: UNKNOWN
Classifier: Framework :: Plone
Classifier: Programming Language :: Python
Classifier: Topic :: Software Development :: Libraries :: Python Modules
